[
  {
    "name": "theme_info",
    "theme_name": "Debut",
    "theme_author": "Shopify",
    "theme_version": "11.2.0",
    "theme_documentation_url": "https://help.shopify.com/manual/using-themes/themes-by-shopify/debut",
    "theme_support_url": "https://support.shopify.com/"
  },
  {
    "name": "Colors",
    "settings": [
      {
        "type": "header",
        "content": "Global"
      },
      {
        "type":"color",
        "id":"body_color",
        "label":"Body color",
        "default":"#ffffff"
      }
    ]
  }
]
